duckatoms/__init__.py
duckatoms/converter.py
duckatoms/db.py
duckatoms/factory.py
duckatoms-0.0.1b1.dist-info/LICENSE
duckatoms-0.0.1b1.dist-info/METADATA
duckatoms-0.0.1b1.dist-info/WHEEL
duckatoms-0.0.1b1.dist-info/RECORD
