Metadata-Version: 2.3
Name: duckatoms
Version: 0.0.1b1
Summary: 
Author: Cedric Hannemann
Author-email: hannemann@fhi.mpg.de
Requires-Python: >=3.11
Classifier: Programming Language :: Python :: 3
Classifier: Programming Language :: Python :: 3.11
Classifier: Programming Language :: Python :: 3.12
Classifier: Programming Language :: Python :: 3.13
Requires-Dist: ase (>=3.25,<4.0)
Requires-Dist: duckdb (>=1.3.1,<2.0.0)
Requires-Dist: pandas (>=2.3.0,<3.0.0)
Requires-Dist: pydantic (>=2.11.7,<3.0.0)
